LICENSE
README.md
setup.py
generators/__init__.py
generators/text/__init__.py
generators/text/azure_textgen.py
generators/text/base_textgen.py
generators/text/cohere_textgen.py
generators/text/hf_textgen.py
generators/text/openai_textgen.py
generators/text/palm_textgen.py
generators/text/providers.py
generators/text/textgen.py
llmx_zk.egg-info/PKG-INFO
llmx_zk.egg-info/SOURCES.txt
llmx_zk.egg-info/dependency_links.txt
llmx_zk.egg-info/requires.txt
llmx_zk.egg-info/top_level.txt